{
    "/js/header-app.js": "/js/header-app.js",
    "/js/app.js": "/js/app.js",
    "/js/payment-stripe.js": "/js/payment-stripe.js",
    "/js/admin.js": "/js/admin.js",
    "/css/admin.css": "/css/admin.css",
    "/css/red.css": "/css/red.css",
    "/css/pdf.css": "/css/pdf.css",
    "/vendor/calendar/js/zabuto_calendar.js": "/vendor/calendar/js/zabuto_calendar.js",
    "/vendor/calendar/css/zabuto_calendar.min.css": "/vendor/calendar/css/zabuto_calendar.min.css",
    "/vendor/leaflet/leaflet-src.esm.js": "/vendor/leaflet/leaflet-src.esm.js",
    "/vendor/leaflet/leaflet-src.esm.js.map": "/vendor/leaflet/leaflet-src.esm.js.map",
    "/vendor/leaflet/leaflet-src.js": "/vendor/leaflet/leaflet-src.js",
    "/vendor/leaflet/leaflet-src.js.map": "/vendor/leaflet/leaflet-src.js.map",
    "/vendor/leaflet/leaflet.css": "/vendor/leaflet/leaflet.css",
    "/vendor/leaflet/leaflet.js": "/vendor/leaflet/leaflet.js",
    "/vendor/leaflet/leaflet.js.map": "/vendor/leaflet/leaflet.js.map",
    "/vendor/leaflet/reference-1.6.0-newleafdoc.html": "/vendor/leaflet/reference-1.6.0-newleafdoc.html",
    "/vendor/leaflet/reference-1.6.0-oldleafdoc.html": "/vendor/leaflet/reference-1.6.0-oldleafdoc.html",
    "/vendor/leaflet/reference-1.6.0.html": "/vendor/leaflet/reference-1.6.0.html",
    "/webfonts/fa-brands-400.eot": "/webfonts/fa-brands-400.eot",
    "/webfonts/fa-brands-400.svg": "/webfonts/fa-brands-400.svg",
    "/webfonts/fa-brands-400.ttf": "/webfonts/fa-brands-400.ttf",
    "/webfonts/fa-brands-400.woff": "/webfonts/fa-brands-400.woff",
    "/webfonts/fa-brands-400.woff2": "/webfonts/fa-brands-400.woff2",
    "/webfonts/fa-regular-400.eot": "/webfonts/fa-regular-400.eot",
    "/webfonts/fa-regular-400.svg": "/webfonts/fa-regular-400.svg",
    "/webfonts/fa-regular-400.ttf": "/webfonts/fa-regular-400.ttf",
    "/webfonts/fa-regular-400.woff": "/webfonts/fa-regular-400.woff",
    "/webfonts/fa-regular-400.woff2": "/webfonts/fa-regular-400.woff2",
    "/webfonts/fa-solid-900.eot": "/webfonts/fa-solid-900.eot",
    "/webfonts/fa-solid-900.svg": "/webfonts/fa-solid-900.svg",
    "/webfonts/fa-solid-900.ttf": "/webfonts/fa-solid-900.ttf",
    "/webfonts/fa-solid-900.woff": "/webfonts/fa-solid-900.woff",
    "/webfonts/fa-solid-900.woff2": "/webfonts/fa-solid-900.woff2"
}
